{
  "tile": "tile_0648.jpg",
  "revisado": false,
  "deteccoes": [
    {
      "id": 33,
      "label": "lixo",
      "bbox": [
        1709,
        1735,
        212,
        201
      ],
      "area": 17511.0,
      "circular": 0.3692,
      "fill": 0.3313
    },
    {
      "id": 34,
      "label": "lixo",
      "bbox": [
        872,
        1661,
        147,
        172
      ],
      "area": 11971.5,
      "circular": 0.3171,
      "fill": 0.2216
    },
    {
      "id": 35,
      "label": "lixo",
      "bbox": [
        1857,
        1500,
        191,
        171
      ],
      "area": 18153.5,
      "circular": 0.3033,
      "fill": 0.3131
    },
    {
      "id": 36,
      "label": "lixo",
      "bbox": [
        973,
        1425,
        174,
        211
      ],
      "area": 14370.0,
      "circular": 0.2725,
      "fill": 0.2281
    },
    {
      "id": 37,
      "label": "lixo",
      "bbox": [
        320,
        1357,
        125,
        235
      ],
      "area": 15778.5,
      "circular": 0.2956,
      "fill": 0.1851
    },
    {
      "id": 38,
      "label": "lixo",
      "bbox": [
        0,
        1296,
        140,
        160
      ],
      "area": 13431.0,
      "circular": 0.2741,
      "fill": 0.3094
    },
    {
      "id": 39,
      "label": "lixo",
      "bbox": [
        1486,
        1237,
        134,
        146
      ],
      "area": 11564.5,
      "circular": 0.4993,
      "fill": 0.3407
    },
    {
      "id": 40,
      "label": "lixo",
      "bbox": [
        229,
        1151,
        242,
        221
      ],
      "area": 14209.5,
      "circular": 0.1755,
      "fill": 0.1585
    },
    {
      "id": 41,
      "label": "lixo",
      "bbox": [
        1297,
        969,
        189,
        160
      ],
      "area": 11657.5,
      "circular": 0.2514,
      "fill": 0.1498
    },
    {
      "id": 42,
      "label": "lixo",
      "bbox": [
        1802,
        793,
        143,
        263
      ],
      "area": 20602.5,
      "circular": 0.3978,
      "fill": 0.3133
    },
    {
      "id": 43,
      "label": "lixo",
      "bbox": [
        13,
        781,
        151,
        212
      ],
      "area": 15205.0,
      "circular": 0.3354,
      "fill": 0.3102
    },
    {
      "id": 44,
      "label": "lixo",
      "bbox": [
        0,
        58,
        170,
        216
      ],
      "area": 13009.5,
      "circular": 0.254,
      "fill": 0.2362
    }
  ],
  "faltantes": []
}
