{
  "tile": "tile_0500.jpg",
  "revisado": false,
  "deteccoes": [
    {
      "id": 51,
      "label": "lixo",
      "bbox": [
        796,
        375,
        278,
        196
      ],
      "area": 24916.0,
      "circular": 0.2117,
      "fill": 0.1567
    },
    {
      "id": 52,
      "label": "lixo",
      "bbox": [
        1025,
        225,
        170,
        200
      ],
      "area": 12013.5,
      "circular": 0.2342,
      "fill": 0.1158
    },
    {
      "id": 53,
      "label": "embauba",
      "bbox": [
        532,
        24,
        392,
        373
      ],
      "area": 66561.0,
      "circular": 0.0888,
      "fill": 0.2443
    }
  ],
  "faltantes": []
}
