{
  "tile": "tile_0635.jpg",
  "revisado": false,
  "embaubas": [
    {
      "bbox": [
        0,
        1770,
        211,
        278
      ],
      "area": 34686.5,
      "poligono": [
        [
          184,
          1772
        ],
        [
          187,
          1773
        ],
        [
          192,
          1776
        ],
        [
          196,
          1780
        ],
        [
          199,
          1785
        ],
        [
          200,
          1787
        ],
        [
          210,
          1817
        ],
        [
          210,
          1819
        ],
        [
          202,
          1974
        ],
        [
          197,
          1984
        ],
        [
          175,
          2027
        ],
        [
          174,
          2028
        ],
        [
          171,
          2029
        ],
        [
          112,
          2047
        ],
        [
          64,
          2047
        ],
        [
          0,
          1982
        ],
        [
          0,
          1838
        ],
        [
          23,
          1827
        ],
        [
          100,
          1793
        ],
        [
          150,
          1771
        ],
        [
          153,
          1770
        ]
      ]
    },
    {
      "bbox": [
        476,
        1182,
        304,
        377
      ],
      "area": 65702.0,
      "poligono": [
        [
          695,
          1182
        ],
        [
          701,
          1184
        ],
        [
          703,
          1185
        ],
        [
          726,
          1203
        ],
        [
          749,
          1224
        ],
        [
          750,
          1226
        ],
        [
          779,
          1371
        ],
        [
          779,
          1373
        ],
        [
          778,
          1380
        ],
        [
          758,
          1471
        ],
        [
          756,
          1477
        ],
        [
          754,
          1481
        ],
        [
          724,
          1527
        ],
        [
          690,
          1546
        ],
        [
          687,
          1547
        ],
        [
          651,
          1558
        ],
        [
          650,
          1558
        ],
        [
          647,
          1557
        ],
        [
          545,
          1518
        ],
        [
          520,
          1504
        ],
        [
          513,
          1498
        ],
        [
          512,
          1496
        ],
        [
          478,
          1385
        ],
        [
          476,
          1375
        ],
        [
          476,
          1370
        ],
        [
          499,
          1295
        ],
        [
          500,
          1292
        ],
        [
          501,
          1290
        ],
        [
          556,
          1205
        ],
        [
          559,
          1204
        ],
        [
          590,
          1194
        ],
        [
          607,
          1189
        ],
        [
          690,
          1182
        ]
      ]
    },
    {
      "bbox": [
        161,
        1101,
        322,
        293
      ],
      "area": 51025.5,
      "poligono": [
        [
          360,
          1101
        ],
        [
          363,
          1102
        ],
        [
          451,
          1148
        ],
        [
          452,
          1150
        ],
        [
          481,
          1213
        ],
        [
          482,
          1221
        ],
        [
          482,
          1223
        ],
        [
          481,
          1225
        ],
        [
          389,
          1361
        ],
        [
          388,
          1362
        ],
        [
          376,
          1367
        ],
        [
          373,
          1368
        ],
        [
          356,
          1373
        ],
        [
          352,
          1374
        ],
        [
          305,
          1385
        ],
        [
          268,
          1393
        ],
        [
          265,
          1392
        ],
        [
          189,
          1331
        ],
        [
          164,
          1288
        ],
        [
          163,
          1286
        ],
        [
          161,
          1281
        ],
        [
          161,
          1279
        ],
        [
          190,
          1163
        ],
        [
          191,
          1161
        ],
        [
          218,
          1137
        ],
        [
          222,
          1134
        ],
        [
          225,
          1133
        ],
        [
          342,
          1104
        ],
        [
          358,
          1101
        ]
      ]
    },
    {
      "bbox": [
        1092,
        924,
        373,
        336
      ],
      "area": 47145.0,
      "poligono": [
        [
          1300,
          924
        ],
        [
          1325,
          930
        ],
        [
          1328,
          931
        ],
        [
          1392,
          954
        ],
        [
          1427,
          975
        ],
        [
          1431,
          978
        ],
        [
          1432,
          979
        ],
        [
          1433,
          981
        ],
        [
          1449,
          1015
        ],
        [
          1464,
          1060
        ],
        [
          1464,
          1062
        ],
        [
          1443,
          1138
        ],
        [
          1400,
          1229
        ],
        [
          1399,
          1231
        ],
        [
          1388,
          1247
        ],
        [
          1385,
          1248
        ],
        [
          1305,
          1259
        ],
        [
          1302,
          1258
        ],
        [
          1285,
          1251
        ],
        [
          1210,
          1212
        ],
        [
          1095,
          1048
        ],
        [
          1094,
          1046
        ],
        [
          1092,
          1034
        ],
        [
          1092,
          1029
        ],
        [
          1095,
          1023
        ],
        [
          1124,
          983
        ],
        [
          1125,
          982
        ],
        [
          1137,
          977
        ],
        [
          1140,
          976
        ],
        [
          1297,
          924
        ]
      ]
    },
    {
      "bbox": [
        613,
        645,
        424,
        317
      ],
      "area": 54732.5,
      "poligono": [
        [
          905,
          646
        ],
        [
          985,
          672
        ],
        [
          988,
          673
        ],
        [
          1007,
          684
        ],
        [
          1021,
          696
        ],
        [
          1022,
          698
        ],
        [
          1036,
          754
        ],
        [
          1036,
          758
        ],
        [
          1033,
          788
        ],
        [
          1029,
          804
        ],
        [
          1028,
          806
        ],
        [
          969,
          881
        ],
        [
          910,
          926
        ],
        [
          864,
          955
        ],
        [
          859,
          957
        ],
        [
          856,
          958
        ],
        [
          817,
          961
        ],
        [
          815,
          961
        ],
        [
          812,
          960
        ],
        [
          628,
          852
        ],
        [
          626,
          848
        ],
        [
          619,
          827
        ],
        [
          613,
          805
        ],
        [
          613,
          803
        ],
        [
          614,
          801
        ],
        [
          628,
          788
        ],
        [
          763,
          663
        ],
        [
          769,
          658
        ],
        [
          772,
          657
        ],
        [
          827,
          650
        ],
        [
          875,
          645
        ]
      ]
    },
    {
      "bbox": [
        211,
        627,
        259,
        341
      ],
      "area": 48979.0,
      "poligono": [
        [
          308,
          627
        ],
        [
          374,
          634
        ],
        [
          377,
          635
        ],
        [
          407,
          649
        ],
        [
          444,
          672
        ],
        [
          445,
          674
        ],
        [
          469,
          877
        ],
        [
          469,
          885
        ],
        [
          468,
          887
        ],
        [
          465,
          892
        ],
        [
          423,
          933
        ],
        [
          399,
          953
        ],
        [
          396,
          954
        ],
        [
          319,
          967
        ],
        [
          316,
          966
        ],
        [
          304,
          961
        ],
        [
          302,
          960
        ],
        [
          284,
          947
        ],
        [
          279,
          943
        ],
        [
          243,
          882
        ],
        [
          242,
          880
        ],
        [
          214,
          813
        ],
        [
          213,
          809
        ],
        [
          211,
          705
        ],
        [
          211,
          702
        ],
        [
          214,
          696
        ],
        [
          304,
          628
        ],
        [
          307,
          627
        ]
      ]
    },
    {
      "bbox": [
        1515,
        626,
        533,
        785
      ],
      "area": 210913.5,
      "poligono": [
        [
          1923,
          627
        ],
        [
          1926,
          628
        ],
        [
          1931,
          630
        ],
        [
          1951,
          662
        ],
        [
          2047,
          818
        ],
        [
          2047,
          1050
        ],
        [
          1936,
          1262
        ],
        [
          1935,
          1263
        ],
        [
          1924,
          1270
        ],
        [
          1730,
          1391
        ],
        [
          1727,
          1392
        ],
        [
          1678,
          1407
        ],
        [
          1662,
          1410
        ],
        [
          1659,
          1409
        ],
        [
          1657,
          1408
        ],
        [
          1650,
          1401
        ],
        [
          1592,
          1333
        ],
        [
          1591,
          1331
        ],
        [
          1584,
          1312
        ],
        [
          1515,
          1084
        ],
        [
          1515,
          1077
        ],
        [
          1519,
          1020
        ],
        [
          1581,
          741
        ],
        [
          1584,
          735
        ],
        [
          1875,
          627
        ],
        [
          1878,
          626
        ]
      ]
    },
    {
      "bbox": [
        1587,
        0,
        411,
        138
      ],
      "area": 29430.0,
      "poligono": [
        [
          1987,
          0
        ],
        [
          1996,
          15
        ],
        [
          1997,
          17
        ],
        [
          1997,
          19
        ],
        [
          1996,
          70
        ],
        [
          1995,
          72
        ],
        [
          1930,
          110
        ],
        [
          1928,
          111
        ],
        [
          1925,
          112
        ],
        [
          1884,
          123
        ],
        [
          1618,
          137
        ],
        [
          1606,
          137
        ],
        [
          1603,
          136
        ],
        [
          1592,
          119
        ],
        [
          1589,
          114
        ],
        [
          1588,
          112
        ],
        [
          1587,
          107
        ],
        [
          1587,
          103
        ],
        [
          1589,
          99
        ],
        [
          1666,
          0
        ]
      ]
    },
    {
      "bbox": [
        957,
        0,
        1032,
        722
      ],
      "area": 266794.0,
      "poligono": [
        [
          1346,
          0
        ],
        [
          1851,
          217
        ],
        [
          1909,
          262
        ],
        [
          1936,
          283
        ],
        [
          1937,
          284
        ],
        [
          1942,
          292
        ],
        [
          1944,
          296
        ],
        [
          1988,
          399
        ],
        [
          1988,
          405
        ],
        [
          1987,
          420
        ],
        [
          1976,
          461
        ],
        [
          1948,
          534
        ],
        [
          1946,
          538
        ],
        [
          1633,
          697
        ],
        [
          1630,
          698
        ],
        [
          1584,
          710
        ],
        [
          1384,
          721
        ],
        [
          1000,
          621
        ],
        [
          997,
          620
        ],
        [
          958,
          583
        ],
        [
          957,
          581
        ],
        [
          957,
          579
        ],
        [
          1140,
          0
        ]
      ]
    },
    {
      "bbox": [
        500,
        0,
        346,
        500
      ],
      "area": 98615.5,
      "poligono": [
        [
          745,
          0
        ],
        [
          833,
          42
        ],
        [
          834,
          44
        ],
        [
          845,
          321
        ],
        [
          845,
          324
        ],
        [
          844,
          326
        ],
        [
          763,
          476
        ],
        [
          722,
          498
        ],
        [
          719,
          499
        ],
        [
          716,
          499
        ],
        [
          693,
          498
        ],
        [
          690,
          497
        ],
        [
          581,
          437
        ],
        [
          528,
          405
        ],
        [
          527,
          404
        ],
        [
          502,
          373
        ],
        [
          500,
          369
        ],
        [
          500,
          362
        ],
        [
          539,
          158
        ],
        [
          552,
          124
        ],
        [
          553,
          122
        ],
        [
          592,
          65
        ],
        [
          602,
          54
        ],
        [
          603,
          53
        ],
        [
          634,
          23
        ],
        [
          640,
          20
        ],
        [
          649,
          16
        ],
        [
          652,
          15
        ],
        [
          715,
          0
        ]
      ]
    },
    {
      "bbox": [
        0,
        0,
        478,
        208
      ],
      "area": 56470.0,
      "poligono": [
        [
          276,
          0
        ],
        [
          433,
          21
        ],
        [
          436,
          22
        ],
        [
          441,
          25
        ],
        [
          448,
          36
        ],
        [
          470,
          73
        ],
        [
          477,
          87
        ],
        [
          477,
          89
        ],
        [
          448,
          150
        ],
        [
          447,
          152
        ],
        [
          330,
          202
        ],
        [
          327,
          203
        ],
        [
          317,
          206
        ],
        [
          310,
          207
        ],
        [
          304,
          207
        ],
        [
          219,
          203
        ],
        [
          14,
          143
        ],
        [
          11,
          142
        ],
        [
          9,
          138
        ],
        [
          0,
          109
        ],
        [
          0,
          0
        ]
      ]
    }
  ],
  "n_candidatos": 14,
  "n_deteccoes": 11,
  "coverage_pct": 23.85838031768799,
  "tempo_s": 0.10319900512695312,
  "memoria_mb": 64.18674659729004
}