{
  "tile": "tile_0086.jpg",
  "embaubas": [
    {
      "bbox": [
        440,
        196,
        189,
        258
      ],
      "area": 15071.0,
      "poligono": [
        [
          500,
          196
        ],
        [
          521,
          201
        ],
        [
          524,
          202
        ],
        [
          543,
          240
        ],
        [
          570,
          296
        ],
        [
          608,
          377
        ],
        [
          612,
          386
        ],
        [
          614,
          391
        ],
        [
          628,
          433
        ],
        [
          628,
          436
        ],
        [
          623,
          450
        ],
        [
          622,
          452
        ],
        [
          619,
          453
        ],
        [
          610,
          450
        ],
        [
          469,
          362
        ],
        [
          468,
          361
        ],
        [
          466,
          357
        ],
        [
          440,
          279
        ],
        [
          440,
          234
        ],
        [
          441,
          221
        ],
        [
          442,
          218
        ],
        [
          443,
          216
        ],
        [
          448,
          213
        ],
        [
          477,
          197
        ],
        [
          480,
          196
        ]
      ]
    }
  ],
  "n_candidatos": 41,
  "n_deteccoes": 1,
  "coverage_pct": 2.2806406021118164,
  "tempo_s": 0.0909881591796875,
  "memoria_mb": 64.06524085998535,
  "falsos_positivos": [],
  "faltantes": [
    {
      "bbox": [
        478,
        1037,
        350,
        350
      ]
    },
    {
      "bbox": [
        856,
        1243,
        246,
        183
      ]
    }
  ]
}