{
  "tile": "tile_0680.jpg",
  "revisado": true,
  "embaubas": [
    {
      "bbox": [
        839,
        1505,
        420,
        471
      ],
      "area": 48133.0,
      "poligono": [
        [
          1119,
          1506
        ],
        [
          1215,
          1569
        ],
        [
          1217,
          1571
        ],
        [
          1218,
          1573
        ],
        [
          1258,
          1685
        ],
        [
          1258,
          1687
        ],
        [
          1257,
          1689
        ],
        [
          1244,
          1700
        ],
        [
          859,
          1974
        ],
        [
          856,
          1975
        ],
        [
          853,
          1974
        ],
        [
          852,
          1972
        ],
        [
          839,
          1933
        ],
        [
          839,
          1930
        ],
        [
          903,
          1762
        ],
        [
          904,
          1760
        ],
        [
          982,
          1615
        ],
        [
          1064,
          1539
        ],
        [
          1113,
          1506
        ],
        [
          1116,
          1505
        ]
      ]
    }
  ],
  "n_candidatos": 13,
  "n_deteccoes": 1,
  "coverage_pct": 10.204887390136719,
  "tempo_s": 0.069305419921875,
  "memoria_mb": 64.12383460998535,
  "falsos_positivos": [
    0
  ],
  "faltantes": []
}